pythoniq/__init__.py
pythoniq-0.0.1.dist-info/LICENSE
pythoniq-0.0.1.dist-info/METADATA
pythoniq-0.0.1.dist-info/WHEEL
pythoniq-0.0.1.dist-info/top_level.txt
pythoniq-0.0.1.dist-info/RECORD
