Metadata-Version: 2.1
Name: pythoniq
Version: 0.0.1
Summary: a pythonic query language
Home-page: https://example.com/pythoniq
Author: Your Name
Author-email: your.email@example.com
Classifier: Programming Language :: Python :: 3
Classifier: License :: OSI Approved :: MIT License
Classifier: Operating System :: OS Independent
Requires-Python: >=3.6
License-File: LICENSE
